dt8852/__init__.py
dt8852/__main__.py
dt8852/dt8852.py
dt8852-1.1.0.dist-info/LICENSE.md
dt8852-1.1.0.dist-info/METADATA
dt8852-1.1.0.dist-info/WHEEL
dt8852-1.1.0.dist-info/entry_points.txt
dt8852-1.1.0.dist-info/top_level.txt
dt8852-1.1.0.dist-info/RECORD
