Metadata-Version: 2.2
Name: dt8852
Version: 1.1.0
Summary: Cross-platform Python package and module for reading and controlling CEM DT-8852 and equivalent Sound Level Meter and Data Logger devices.
Home-page: https://codeberg.org/randysimons/dt8852
Author: Randy Simons
License: GNU General Public License v3 or later (GPLv3+)
Project-URL: Bug Tracker, https://codeberg.org/randysimons/dt8852/issues
Classifier: Operating System :: OS Independent
Classifier: Programming Language :: Python :: 3
Classifier: Topic :: System :: Hardware
Classifier: License :: OSI Approved :: GNU General Public License v3 or later (GPLv3+)
Requires-Python: >=3.7
License-File: LICENSE.md
Requires-Dist: pyserial>=3.4
